cursor_init/__init__.py
cursor_init/application.py
cursor_init/services/__init__.py
cursor_init/services/common/__init__.py
cursor_init/services/common/file_utils.py
cursor_init/services/docs/__init__.py
cursor_init/services/docs/service.py
cursor_init/services/docs/typer.py
cursor_init/services/mcp/__init__.py
cursor_init/services/mcp/typer.py
cursor_init/templates/__init__.py
cursor_init/templates/profile/__init__.py
cursor_init/templates/profile/default/.cursorrules
cursor_init/templates/profile/default/__init__.py
cursor_init/templates/profile/default/.cursor/mcp.json
cursor_init/templates/profile/default/.cursor/rules/development.mdc
cursor_init/templates/profile/default/.cursor/rules/directory-structure.mdc
cursor_init/templates/profile/default/.cursor/rules/git.mdc
cursor_init/templates/profile/default/.cursor/rules/task-check.mdc
cursor_init/templates/profile/default/.cursor/rules/task.mdc
cursor_init/templates/profile/default/.cursor/rules/tech-stack.mdc
cursor_init/templates/profile/default/.cursor/rules/think.mdc
cursor_init/templates/profile/default/.cursor-init/docs/directory-structure.md
cursor_init/templates/profile/default/.cursor-init/docs/mvp-design.md
cursor_init/templates/profile/default/.cursor-init/docs/teck-stack.md
cursor_init/templates/profile/default/.cursor-init/docs/workflow.md
cursor_init-0.1.9.dist-info/METADATA
cursor_init-0.1.9.dist-info/WHEEL
cursor_init-0.1.9.dist-info/entry_points.txt
cursor_init-0.1.9.dist-info/top_level.txt
cursor_init-0.1.9.dist-info/RECORD
