Metadata-Version: 2.4
Name: cursor-init
Version: 0.1.9
Summary: 프로젝트 규칙 파일을 간편하게 세팅하는 CLI
Requires-Python: >=3.10
Requires-Dist: requests>=2.32.3
Requires-Dist: typer
Requires-Dist: types-requests>=2.32.0.20250328
